{
  "appPageId" : "7f1e9589-70ef-4b09-980c-437b12f567f8",
  "componentName" : "siteforce:sldsOneColLayout",
  "id" : "24fc2b82-49c3-414a-aeb5-7f6535dc21c6",
  "label" : "Action Plan Liste",
  "regions" : [ {
    "id" : "33451257-4151-4526-ab7b-000a2da67255",
    "regionName" : "header",
    "type" : "region"
  }, {
    "components" : [ {
      "componentAttributes" : {
        "enableInlineEdit" : true,
        "filterName" : "{!filterId}",
        "layout" : "FULL",
        "pageSize" : 25,
        "scope" : "{!objectName}",
        "showActionBar" : true,
        "showChartsPanel" : true,
        "showDisplay" : "showall",
        "showFilterPanel" : true,
        "showImageIcon" : true,
        "showManualRefreshButton" : true,
        "showObjectName" : true,
        "showPinnedList" : true,
        "showSearchBar" : true
      },
      "componentName" : "forceCommunity:objectHome",
      "id" : "e6120ee4-db0a-4255-8e2e-3a7ee5bed57e",
      "renderPriority" : "NEUTRAL",
      "renditionMap" : { },
      "type" : "component"
    } ],
    "id" : "a6272ac8-e812-496c-9054-515ec6418924",
    "regionName" : "content",
    "type" : "region"
  }, {
    "id" : "76f61158-bdf5-4971-a122-21206fade185",
    "regionName" : "footer",
    "type" : "region"
  } ],
  "themeLayoutType" : "Inner",
  "type" : "view",
  "viewType" : "list-07r"
}